deep_transcribe/__init__.py
deep_transcribe/__main__.py
deep_transcribe/cli_main.py
deep_transcribe/py.typed
deep_transcribe/transcribe_commands.py
deep_transcribe/transcribe_options.py
deep_transcribe-0.1.5.dist-info/METADATA
deep_transcribe-0.1.5.dist-info/WHEEL
deep_transcribe-0.1.5.dist-info/entry_points.txt
deep_transcribe-0.1.5.dist-info/licenses/LICENSE
deep_transcribe-0.1.5.dist-info/RECORD
