Metadata-Version: 2.4
Name: deep-transcribe
Version: 0.1.5
Summary: High-quality transcription, formatting, and analysis of videos and podcasts
Project-URL: Repository, https://github.com/jlevy/deep-transcribe
Author-email: Joshua Levy <joshua@cal.berkeley.edu>
License-Expression: AGPL-3.0-or-later
License-File: LICENSE
Classifier: Development Status :: 4 - Beta
Classifier: Intended Audience :: Developers
Classifier: Operating System :: OS Independent
Classifier: Programming Language :: Python
Classifier: Programming Language :: Python :: 3
Classifier: Programming Language :: Python :: 3.11
Classifier: Programming Language :: Python :: 3.12
Classifier: Programming Language :: Python :: 3.13
Classifier: Typing :: Typed
Requires-Python: <4.0,>=3.11
Requires-Dist: flowmark>=0.5.2
Requires-Dist: kash-media>=0.3.14
Requires-Dist: prettyfmt>=0.2.1
Requires-Dist: rich-argparse>=1.7.0
Requires-Dist: rich>=14.0.0
